[{
	{
		"id": "mckismetlab-mainserver",
		"name": "mcKismetLab Main Mods Server",
		"icon": "",
		"version": "1.0.0",
		"address": "mcKismetLab.net",
		"minecraftVersion": "1.12.2",
		"minecraftType": "minecraftModpack",
		"minecraftTypeID": "1",
		"modpacks": {
			"name": "FTB Sky Adventures",
			"projectID": "304542",
			"filesID": "2658207",
			"version": "1.4.0",
			"modLoaders": {
				"id": "forge-14.23.5.2796",
				"name": "net.minecraftforge:forge:1.12.2-14.23.5.2796",
				"version": "1.12.2-14.23.5.2796",
				"download": {
					"artifact": {
						"sha1": "",
						"size": "",
						"url": "",
						"path": "net/minecraftforge/forge/1.12.2-14.23.5.2796/forge-1.12.2-14.23.5.2796.jar"
					}
				}
			},
			"modules": [
				{
					"id": "ItemBlacklist-1.4.3.jar",
					"name": "Item Blacklistr",
					"version": "1.4.3",
					"type": "ForgeMod",
					"action": "ADD",
					"download": {
						"projectID": "237226",
						"filesID": "2776296"
					}
				}
			],
			"time": "2020/6/27 上午10:19:08"
		},
		{
			"id": "mckismetlab-mainserver",
			"name": "mcKismetLab Main Mods Server"
		}
}]
